README.md
setup.py
hiw.egg-info/PKG-INFO
hiw.egg-info/SOURCES.txt
hiw.egg-info/dependency_links.txt
hiw.egg-info/top_level.txt
online_users/__init__.py
online_users/admin.py
online_users/middleware.py
online_users/models.py
online_users/migrations/0001_initial.py
online_users/migrations/__init__.py
online_users/tests/__init__.py
online_users/tests/test_middleware.py
online_users/tests/test_models.py