Metadata-Version: 2.1
Name: hiw
Version: 0.0.1
Summary: python for abc
Home-page: UNKNOWN
Author: Duc_Ngoc
Author-email: nguyenducngoc167@gmail.com
License: UNKNOWN
Platform: UNKNOWN
Classifier: Programming Language :: Python :: 3
Classifier: License :: OSI Approved :: MIT License
Classifier: Operating System :: OS Independent
